{"metadata": {"dataVersion": "2", "matchId": "NA1_4055809243", "participants": ["JF77qXxvJVLRNsMBh6GD4gAB0iDggHKPkTgBj7azoDICf-wsQKRLc-iublCPndvFC6N0GGmYeAdnmQ", "9Y6ck-DOgT_QxtsP6g0LKVHaDGAYDV0AJBlQkNxYHqjQxrpGvZvpKyeqwSSNRWp-63wOVaxR9D7qGA", "hvQzNBE11nlPh3jMdYDIT3LR4o4HY59lSQPXwLOtsD-NSQfAXJzOFXaPGhDSlaVypabundI7BFLJnQ", "ZioJPINUMQH-A0hR52DTtlJZK6244QxX-FIZ6TLzBOFS2hIqLnhSIXVdNt90GPR_g7o8gWh9DorhYA", "6BlInRmPv5KB0RlxEuRnD0-Ys5h94m6pLKMhGKI6OF059J1ElMnruF6doLYe1aLprhdpwoMN6bq7cw", "QxDrFSB4JTAmOsmAkGMLvFnUWYElWPdktiB9dnkOPcqLuecUxTbMGgnAqp2jodPkJLEece8fNHai0A", "1nyzmxLyhiaML7MqFZY0IYxOam8O_xAKAHo1QNVMNBp-DrAqu8zkIQCNxcsOGsBshlTZ2ByqE7fmYQ", "vnTza7GKACnddu8YEMsM1TFJWGxmEV88ajFPnQ_yujAfxhnuKceEnU0k20T9rxnYE4zahwp4uyRXVA", "DlhFyUDdIjGtLPxuGkoTo0c0XPHXZ1pyM75Tfbju4Wvc8XRdE2aSo2BRtykpOyuix6bRvuplFYzZkg", "38WQGMdvGsE0pqibCVOM6Q5W4aWrcOr5Z8xofm2DVvbHDaHRFQ-Vudz-aTdKVMa9A6bmDZH7-H_Qqw"]}, "info": {"frameInterval": 60000, "frames": [{"events": [{"realTimestamp": 1632856084596, "timestamp": 0, "type": "PAUSE_END"}], "participantFrames": {"1": {"championStats": {"abilityHaste": 0, "abilityPower": 0, "armor": 35, "armorPen": 0, "armorPenPercent": 0, "attackDamage": 25, "attackSpeed": 100, "bonusArmorPenPercent": 0, "bonusMagicPenPercent": 0, "ccReduction": 0, "cooldownReduction": 0, "health": 576, "healthMax": 576, "healthRegen": 0, "lifesteal": 0, "magicPen": 0, "magicPenPercent": 0, "magicResist": 32, "movementSpeed": 340, "omnivamp": 0, "physicalVamp": 0, "power": 339, "powerMax": 339, "powerRegen": 0, "spellVamp": 0}, "currentGold": 500, "damageStats": {"magicDamageDone": 0, "magicDamageDoneToChampions": 0, "magicDamageTaken": 0, "physicalDamageDone": 0, "physicalDamageDoneToChampions": 0, "physicalDamageTaken": 0, "totalDamageDone": 0, "totalDamageDoneToChampions": 0, "totalDamageTaken": 0, "trueDamageDone": 0, "trueDamageDoneToChampions": 0, "trueDamageTaken": 0}, "goldPerSecond": 0, "jungleMinionsKilled": 0, "level": 1, "minionsKilled": 0, "participantId": 1, "position": {"x": 554, "y": 581}, "timeEnemySpentControlled": 0, "totalGold": 500, "xp": 0}, "2": {"championStats": {"abilityHaste": 0, "abilityPower": 0, "armor": 32, "armorPen": 0, "armorPenPercent": 0, "attackDamage": 25, "attackSpeed": 100, "bonusArmorPenPercent": 0, "bonusMagicPenPercent": 0, "ccReduction": 0, "cooldownReduction": 0, "health": 585, "healthMax": 585, "healthRegen": 0, "lifesteal": 0, "magicPen": 0, "magicPenPercent": 0, "magicResist": 32, "movementSpeed": 340, "omnivamp": 0, "physicalVamp": 0, "power": 280, "powerMax": 280, "powerRegen": 0, "spellVamp": 0}, "currentGold": 500, "damageStats": {"magicDamageDone": 0, "magicDamageDoneToChampions": 0, "magicDamageTaken": 0, "physicalDamageDone": 0, "physicalDamageDoneToChampions": 0, "physicalDamageTaken": 0, "totalDamageDone": 0, "totalDamageDoneToChampions": 0, "totalDamageTaken": 0, "trueDamageDone": 0, "trueDamageDoneToChampions": 0, "trueDamageTaken": 0}, "goldPerSecond": 0, "jungleMinionsKilled": 0, "level": 1, "minionsKilled": 0, "participantId": 2, "position": {"x": 557, "y": 345}, "timeEnemySpentControlled": 0, "totalGold": 500, "xp": 0}, "3": {"championStats": {"abilityHaste": 0, "abilityPower": 0, "armor": 27, "armorPen": 0, "armorPenPercent": 0, "attackDamage": 25, "attackSpeed": 100, "bonusArmorPenPercent": 0, "bonusMagicPenPercent": 0, "ccReduction": 0, "cooldownReduction": 0, "health": 525, "healthMax": 525, "healthRegen": 0, "lifesteal": 0, "magicPen": 0, "magicPenPercent": 0, "magicResist": 32, "movementSpeed": 340, "omnivamp": 0, "physicalVamp": 0, "power": 310, "powerMax": 310, "powerRegen": 0, "spellVamp": 0}, "currentGold": 500, "damageStats": {"magicDamageDone": 0, "magicDamageDoneToChampions": 0, "magicDamageTaken": 0, "physicalDamageDone": 0, "physicalDamageDoneToChampions": 0, "physicalDamageTaken": 0, "totalDamageDone": 0, "totalDamageDoneToChampions": 0, "totalDamageTaken": 0, "trueDamageDone": 0, "trueDamageDoneToChampions": 0, "trueDamageTaken": 0}, "goldPerSecond": 0, "jungleMinionsKilled": 0, "level": 1, "minionsKilled": 0, "participantId": 3, "position": {"x": 335, "y": 269}, "timeEnemySpentControlled": 0, "totalGold": 500, "xp": 0}, "4": {"championStats": {"abilityHaste": 0, "abilityPower": 0, "armor": 26, "armorPen": 0, "armorPenPercent": 0, "attackDamage": 25, "attackSpeed": 100, "bonusArmorPenPercent": 0, "bonusMagicPenPercent": 0, "ccReduction": 0, "cooldownReduction": 0, "health": 570, "healthMax": 570, "healthRegen": 0, "lifesteal": 0, "magicPen": 0, "magicPenPercent": 0, "magicResist": 30, "movementSpeed": 325, "omnivamp": 0, "physicalVamp": 0, "power": 280, "powerMax": 280, "powerRegen": 0, "spellVamp": 0}, "currentGold": 500, "damageStats": {"magicDamageDone": 0, "magicDamageDoneToChampions": 0, "magicDamageTaken": 0, "physicalDamageDone": 0, "physicalDamageDoneToChampions": 0, "physicalDamageTaken": 0, "totalDamageDone": 0, "totalDamageDoneToChampions": 0, "totalDamageTaken": 0, "trueDamageDone": 0, "trueDamageDoneToChampions": 0, "trueDamageTaken": 0}, "goldPerSecond": 0, "jungleMinionsKilled": 0, "level": 1, "minionsKilled": 0, "participantId": 4, "position": {"x": 194, "y": 457}, "timeEnemySpentControlled": 0, "totalGold": 500, "xp": 0}, "5": {"championStats": {"abilityHaste": 0, "abilityPower": 0, "armor": 26, "armorPen": 0, "armorPenPercent": 0, "attackDamage": 25, "attackSpeed": 100, "bonusArmorPenPercent": 0, "bonusMagicPenPercent": 0, "ccReduction": 0, "cooldownReduction": 0, "health": 480, "healthMax": 480, "healthRegen": 0, "lifesteal": 0, "magicPen": 0, "magicPenPercent": 0, "magicResist": 30, "movementSpeed": 325, "omnivamp": 0, "physicalVamp": 0, "power": 340, "powerMax": 340, "powerRegen": 0, "spellVamp": 0}, "currentGold": 500, "damageStats": {"magicDamageDone": 0, "magicDamageDoneToChampions": 0, "magicDamageTaken": 0, "physicalDamageDone": 0, "physicalDamageDoneToChampions": 0, "physicalDamageTaken": 0, "totalDamageDone": 0, "totalDamageDoneToChampions": 0, "totalDamageTaken": 0, "trueDamageDone": 0, "trueDamageDoneToChampions": 0, "trueDamageTaken": 0}, "goldPerSecond": 0, "jungleMinionsKilled": 0, "level": 1, "minionsKilled": 0, "participantId": 5, "position": {"x": 329, "y": 650}, "timeEnemySpentControlled": 0, "totalGold": 500, "xp": 0}, "6": {"championStats": {"abilityHaste": 0, "abilityPower": 0, "armor": 26, "armorPen": 0, "armorPenPercent": 0, "attackDamage": 25, "attackSpeed": 100, "bonusArmorPenPercent": 0, "bonusMagicPenPercent": 0, "ccReduction": 0, "cooldownReduction": 0, "health": 600, "healthMax": 600, "healthRegen": 0, "lifesteal": 0, "magicPen": 0, "magicPenPercent": 0, "magicResist": 26, "movementSpeed": 335, "omnivamp": 0, "physicalVamp": 0, "power": 330, "powerMax": 330, "powerRegen": 0, "spellVamp": 0}, "currentGold": 500, "damageStats": {"magicDamageDone": 0, "magicDamageDoneToChampions": 0, "magicDamageTaken": 0, "physicalDamageDone": 0, "physicalDamageDoneToChampions": 0, "physicalDamageTaken": 0, "totalDamageDone": 0, "totalDamageDoneToChampions": 0, "totalDamageTaken": 0, "trueDamageDone": 0, "trueDamageDoneToChampions": 0, "trueDamageTaken": 0}, "goldPerSecond": 0, "jungleMinionsKilled": 0, "level": 1, "minionsKilled": 0, "participantId": 6, "position": {"x": 14180, "y": 14271}, "timeEnemySpentControlled": 0, "totalGold": 500, "xp": 0}, "7": {"championStats": {"abilityHaste": 0, "abilityPower": 0, "armor": 30, "armorPen": 0, "armorPenPercent": 0, "attackDamage": 25, "attackSpeed": 100, "bonusArmorPenPercent": 0, "bonusMagicPenPercent": 0, "ccReduction": 0, "cooldownReduction": 0, "health": 585, "healthMax": 585, "healthRegen": 0, "lifesteal": 0, "magicPen": 0, "magicPenPercent": 0, "magicResist": 32, "movementSpeed": 340, "omnivamp": 0, "physicalVamp": 0, "power": 295, "powerMax": 295, "powerRegen": 0, "spellVamp": 0}, "currentGold": 500, "damageStats": {"magicDamageDone": 0, "magicDamageDoneToChampions": 0, "magicDamageTaken": 0, "physicalDamageDone": 0, "physicalDamageDoneToChampions": 0, "physicalDamageTaken": 0, "totalDamageDone": 0, "totalDamageDoneToChampions": 0, "totalDamageTaken": 0, "trueDamageDone": 0, "trueDamageDoneToChampions": 0, "trueDamageTaken": 0}, "goldPerSecond": 0, "jungleMinionsKilled": 0, "level": 1, "minionsKilled": 0, "participantId": 7, "position": {"x": 14176, "y": 14506}, "timeEnemySpentControlled": 0, "totalGold": 500, "xp": 0}, "8": {"championStats": {"abilityHaste": 0, "abilityPower": 0, "armor": 28, "armorPen": 0, "armorPenPercent": 0, "attackDamage": 25, "attackSpeed": 100, "bonusArmorPenPercent": 0, "bonusMagicPenPercent": 0, "ccReduction": 0, "cooldownReduction": 0, "health": 590, "healthMax": 590, "healthRegen": 0, "lifesteal": 0, "magicPen": 0, "magicPenPercent": 0, "magicResist": 32, "movementSpeed": 335, "omnivamp": 0, "physicalVamp": 0, "power": 320, "powerMax": 320, "powerRegen": 0, "spellVamp": 0}, "currentGold": 500, "damageStats": {"magicDamageDone": 0, "magicDamageDoneToChampions": 0, "magicDamageTaken": 0, "physicalDamageDone": 0, "physicalDamageDoneToChampions": 0, "physicalDamageTaken": 0, "totalDamageDone": 0, "totalDamageDoneToChampions": 0, "totalDamageTaken": 0, "trueDamageDone": 0, "trueDamageDoneToChampions": 0, "trueDamageTaken": 0}, "goldPerSecond": 0, "jungleMinionsKilled": 0, "level": 1, "minionsKilled": 0, "participantId": 8, "position": {"x": 14398, "y": 14582}, "timeEnemySpentControlled": 0, "totalGold": 500, "xp": 0}, "9": {"championStats": {"abilityHaste": 0, "abilityPower": 0, "armor": 29, "armorPen": 0, "armorPenPercent": 0, "attackDamage": 25, "attackSpeed": 100, "bonusArmorPenPercent": 0, "bonusMagicPenPercent": 0, "ccReduction": 0, "cooldownReduction": 0, "health": 605, "healthMax": 605, "healthRegen": 0, "lifesteal": 0, "magicPen": 0, "magicPenPercent": 0, "magicResist": 30, "movementSpeed": 330, "omnivamp": 0, "physicalVamp": 0, "power": 360, "powerMax": 360, "powerRegen": 0, "spellVamp": 0}, "currentGold": 500, "damageStats": {"magicDamageDone": 0, "magicDamageDoneToChampions": 0, "magicDamageTaken": 0, "physicalDamageDone": 0, "physicalDamageDoneToChampions": 0, "physicalDamageTaken": 0, "totalDamageDone": 0, "totalDamageDoneToChampions": 0, "totalDamageTaken": 0, "trueDamageDone": 0, "trueDamageDoneToChampions": 0, "trueDamageTaken": 0}, "goldPerSecond": 0, "jungleMinionsKilled": 0, "level": 1, "minionsKilled": 0, "participantId": 9, "position": {"x": 14539, "y": 14394}, "timeEnemySpentControlled": 0, "totalGold": 500, "xp": 0}, "10": {"championStats": {"abilityHaste": 0, "abilityPower": 0, "armor": 47, "armorPen": 0, "armorPenPercent": 0, "attackDamage": 25, "attackSpeed": 100, "bonusArmorPenPercent": 0, "bonusMagicPenPercent": 0, "ccReduction": 0, "cooldownReduction": 0, "health": 576, "healthMax": 576, "healthRegen": 0, "lifesteal": 0, "magicPen": 0, "magicPenPercent": 0, "magicResist": 32, "movementSpeed": 335, "omnivamp": 0, "physicalVamp": 0, "power": 302, "powerMax": 302, "powerRegen": 0, "spellVamp": 0}, "currentGold": 500, "damageStats": {"magicDamageDone": 0, "magicDamageDoneToChampions": 0, "magicDamageTaken": 0, "physicalDamageDone": 0, "physicalDamageDoneToChampions": 0, "physicalDamageTaken": 0, "totalDamageDone": 0, "totalDamageDoneToChampions": 0, "totalDamageTaken": 0, "trueDamageDone": 0, "trueDamageDoneToChampions": 0, "trueDamageTaken": 0}, "goldPerSecond": 0, "jungleMinionsKilled": 0, "level": 1, "minionsKilled": 0, "participantId": 10, "position": {"x": 14404, "y": 14201}, "timeEnemySpentControlled": 0, "totalGold": 500, "xp": 0}}, "timestamp": 0}, {"events": [{"itemId": 3858, "participantId": 10, "timestamp": 5428, "type": "ITEM_PURCHASED"}, {"itemId": 2003, "participantId": 10, "timestamp": 5428, "type": "ITEM_PURCHASED"}, {"itemId": 2003, "participantId": 10, "timestamp": 5428, "type": "ITEM_PURCHASED"}, {"itemId": 1039, "participantId": 2, "timestamp": 5527, "type": "ITEM_PURCHASED"}, {"itemId": 3340, "participantId": 2, "timestamp": 6220, "type": "ITEM_PURCHASED"}, {"itemId": 1039, "participantId": 7, "timestamp": 6484, "type": "ITEM_PURCHASED"}, {"itemId": 2031, "participantId": 7, "timestamp": 6782, "type": "ITEM_PURCHASED"}, {"itemId": 2031, "participantId": 2, "timestamp": 6914, "type": "ITEM_PURCHASED"}, {"itemId": 3340, "participantId": 7, "timestamp": 7244, "type": "ITEM_PURCHASED"}, {"itemId": 1036, "participantId": 9, "timestamp": 8169, "type": "ITEM_PURCHASED"}, {"itemId": 2003, "participantId": 9, "timestamp": 8862, "type": "ITEM_PURCHASED"}, {"itemId": 2003, "participantId": 9, "timestamp": 8994, "type": "ITEM_PURCHASED"}, {"itemId": 2003, "participantId": 9, "timestamp": 9159, "type": "ITEM_PURCHASED"}, {"itemId": 1036, "participantId": 8, "timestamp": 9225, "type": "ITEM_PURCHASED"}, {"itemId": 2031, "participantId": 8, "timestamp": 9225, "type": "ITEM_PURCHASED"}, {"itemId": 3340, "participantId": 8, "timestamp": 9952, "type": "ITEM_PURCHASED"}, {"itemId": 2033, "participantId": 6, "timestamp": 10183, "type": "ITEM_PURCHASED"}, {"itemId": 3340, "participantId": 6, "timestamp": 10612, "type": "ITEM_PURCHASED"}, {"itemId": 1055, "participantId": 4, "timestamp": 10645, "type": "ITEM_PURCHASED"}, {"itemId": 2003, "participantId": 4, "timestamp": 10645, "type": "ITEM_PURCHASED"}, {"itemId": 3340, "participantId": 4, "timestamp": 11669, "type": "ITEM_PURCHASED"}, {"itemId": 1055, "participantId": 1, "timestamp": 11768, "type": "ITEM_PURCHASED"}, {"itemId": 2003, "participantId": 1, "timestamp": 11768, "type": "ITEM_PURCHASED"}, {"itemId": 3340, "participantId": 1, "timestamp": 12396, "type": "ITEM_PURCHASED"}, {"itemId": 1056, "participantId": 3, "timestamp": 12627, "type": "ITEM_PURCHASED"}, {"itemId": 2003, "participantId": 3, "timestamp": 12627, "type": "ITEM_PURCHASED"}, {"itemId": 2003, "participantId": 3, "timestamp": 12627, "type": "ITEM_PURCHASED"}, {"itemId": 3340, "participantId": 3, "timestamp": 13057, "type": "ITEM_PURCHASED"}, {"levelUpType": "NORMAL", "participantId": 4, "skillSlot": 2, "timestamp": 13520, "type": "SKILL_LEVEL_UP"}, {"creatorId": 10, "timestamp": 35353, "type": "WARD_PLACED", "wardType": "YELLOW_TRINKET"}, {"killerId": 2, "timestamp": 37632, "type": "WARD_KILL", "wardType": "YELLOW_TRINKET"}, {"creatorId": 4, "timestamp": 40736, "type": "WARD_PLACED", "wardType": "YELLOW_TRINKET"}, {"itemId": 3340, "participantId": 10, "timestamp": 51008, "type": "ITEM_DESTROYED"}, {"itemId": 3364, "participantId": 10, "timestamp": 51008, "type": "ITEM_PURCHASED"}], "participantFrames": {"1": {"championStats": {"abilityHaste": 0, "abilityPower": 0, "armor": 41, "armorPen": 0, "armorPenPercent": 0, "attackDamage": 86, "attackSpeed": 100, "bonusArmorPenPercent": 0, "bonusMagicPenPercent": 0, "ccReduction": 0, "cooldownReduction": 0, "health": 656, "healthMax": 656, "healthRegen": 17, "lifesteal": 0, "magicPen": 0, "magicPenPercent": 0, "magicResist": 32, "movementSpeed": 340, "omnivamp": 2, "physicalVamp": 0, "power": 339, "powerMax": 339, "powerRegen": 16, "spellVamp": 0}, "currentGold": 0, "damageStats": {"magicDamageDone": 0, "magicDamageDoneToChampions": 0, "magicDamageTaken": 0, "physicalDamageDone": 1, "physicalDamageDoneToChampions": 0, "physicalDamageTaken": 0, "totalDamageDone": 1, "totalDamageDoneToChampions": 0, "totalDamageTaken": 0, "trueDamageDone": 0, "trueDamageDoneToChampions": 0, "trueDamageTaken": 0}, "goldPerSecond": 0, "jungleMinionsKilled": 0, "level": 1, "minionsKilled": 0, "participantId": 1, "position": {"x": 4399, "y": 7080}, "timeEnemySpentControlled": 0, "totalGold": 500, "xp": 11}, "2": {"championStats": {"abilityHaste": 0, "abilityPower": 9, "armor": 38, "armorPen": 0, "armorPenPercent": 0, "attackDamage": 58, "attackSpeed": 110, "bonusArmorPenPercent": 0, "bonusMagicPenPercent": 0, "ccReduction": 0, "cooldownReduction": 0, "health": 585, "healthMax": 585, "healthRegen": 18, "lifesteal": 0, "magicPen": 0, "magicPenPercent": 0, "magicResist": 32, "movementSpeed": 340, "omnivamp": 0, "physicalVamp": 0, "power": 280, "powerMax": 280, "powerRegen": 14, "spellVamp": 0}, "currentGold": 10, "damageStats": {"magicDamageDone": 0, "magicDamageDoneToChampions": 0, "magicDamageTaken": 0, "physicalDamageDone": 1, "physicalDamageDoneToChampions": 0, "physicalDamageTaken": 0, "totalDamageDone": 1, "totalDamageDoneToChampions": 0, "totalDamageTaken": 0, "trueDamageDone": 0, "trueDamageDoneToChampions": 0, "trueDamageTaken": 0}, "goldPerSecond": 0, "jungleMinionsKilled": 0, "level": 1, "minionsKilled": 1, "participantId": 2, "position": {"x": 7077, "y": 4396}, "timeEnemySpentControlled": 0, "totalGold": 510, "xp": 11}, "3": {"championStats": {"abilityHaste": 0, "abilityPower": 24, "armor": 33, "armorPen": 0, "armorPenPercent": 0, "attackDamage": 61, "attackSpeed": 100, "bonusArmorPenPercent": 0, "bonusMagicPenPercent": 0, "ccReduction": 5, "cooldownReduction": 0, "health": 595, "healthMax": 595, "healthRegen": 18, "lifesteal": 0, "magicPen": 0, "magicPenPercent": 0, "magicResist": 32, "movementSpeed": 340, "omnivamp": 0, "physicalVamp": 0, "power": 310, "powerMax": 310, "powerRegen": 16, "spellVamp": 0}, "currentGold": 0, "damageStats": {"magicDamageDone": 0, "magicDamageDoneToChampions": 0, "magicDamageTaken": 0, "physicalDamageDone": 1, "physicalDamageDoneToChampions": 0, "physicalDamageTaken": 0, "totalDamageDone": 1, "totalDamageDoneToChampions": 0, "totalDamageTaken": 0, "trueDamageDone": 0, "trueDamageDoneToChampions": 0, "trueDamageTaken": 0}, "goldPerSecond": 0, "jungleMinionsKilled": 0, "level": 1, "minionsKilled": 0, "participantId": 3, "position": {"x": 6464, "y": 6636}, "timeEnemySpentControlled": 0, "totalGold": 500, "xp": 11}, "4": {"championStats": {"abilityHaste": 0, "abilityPower": 0, "armor": 32, "armorPen": 0, "armorPenPercent": 0, "attackDamage": 72, "attackSpeed": 110, "bonusArmorPenPercent": 0, "bonusMagicPenPercent": 0, "ccReduction": 0, "cooldownReduction": 0, "health": 650, "healthMax": 650, "healthRegen": 7, "lifesteal": 0, "magicPen": 0, "magicPenPercent": 0, "magicResist": 30, "movementSpeed": 325, "omnivamp": 2, "physicalVamp": 0, "power": 280, "powerMax": 280, "powerRegen": 13, "spellVamp": 0}, "currentGold": 0, "damageStats": {"magicDamageDone": 0, "magicDamageDoneToChampions": 0, "magicDamageTaken": 0, "physicalDamageDone": 0, "physicalDamageDoneToChampions": 0, "physicalDamageTaken": 0, "totalDamageDone": 0, "totalDamageDoneToChampions": 0, "totalDamageTaken": 0, "trueDamageDone": 0, "trueDamageDoneToChampions": 0, "trueDamageTaken": 0}, "goldPerSecond": 0, "jungleMinionsKilled": 0, "level": 1, "minionsKilled": 0, "participantId": 4, "position": {"x": 8009, "y": 3524}, "timeEnemySpentControlled": 0, "totalGold": 500, "xp": 11}, "5": {"championStats": {"abilityHaste": 0, "abilityPower": 0, "armor": 38, "armorPen": 0, "armorPenPercent": 0, "attackDamage": 49, "attackSpeed": 100, "bonusArmorPenPercent": 0, "bonusMagicPenPercent": 0, "ccReduction": 0, "cooldownReduction": 0, "health": 480, "healthMax": 480, "healthRegen": 11, "lifesteal": 0, "magicPen": 0, "magicPenPercent": 0, "magicResist": 30, "movementSpeed": 698, "omnivamp": 0, "physicalVamp": 0, "power": 340, "powerMax": 340, "powerRegen": 23, "spellVamp": 0}, "currentGold": 500, "damageStats": {"magicDamageDone": 0, "magicDamageDoneToChampions": 0, "magicDamageTaken": 0, "physicalDamageDone": 0, "physicalDamageDoneToChampions": 0, "physicalDamageTaken": 0, "totalDamageDone": 0, "totalDamageDoneToChampions": 0, "totalDamageTaken": 0, "trueDamageDone": 0, "trueDamageDoneToChampions": 0, "trueDamageTaken": 0}, "goldPerSecond": 0, "jungleMinionsKilled": 0, "level": 1, "minionsKilled": 0, "participantId": 5, "position": {"x": 394, "y": 462}, "timeEnemySpentControlled": 0, "totalGold": 500, "xp": 0}, "6": {"championStats": {"abilityHaste": 0, "abilityPower": 0, "armor": 32, "armorPen": 0, "armorPenPercent": 0, "attackDamage": 60, "attackSpeed": 103, "bonusArmorPenPercent": 0, "bonusMagicPenPercent": 0, "ccReduction": 0, "cooldownReduction": 0, "health": 600, "healthMax": 600, "healthRegen": 10, "lifesteal": 0, "magicPen": 0, "magicPenPercent": 0, "magicResist": 26, "movementSpeed": 335, "omnivamp": 0, "physicalVamp": 0, "power": 330, "powerMax": 330, "powerRegen": 16, "spellVamp": 0}, "currentGold": 0, "damageStats": {"magicDamageDone": 0, "magicDamageDoneToChampions": 0, "magicDamageTaken": 0, "physicalDamageDone": 0, "physicalDamageDoneToChampions": 0, "physicalDamageTaken": 0, "totalDamageDone": 0, "totalDamageDoneToChampions": 0, "totalDamageTaken": 0, "trueDamageDone": 0, "trueDamageDoneToChampions": 0, "trueDamageTaken": 0}, "goldPerSecond": 0, "jungleMinionsKilled": 0, "level": 1, "minionsKilled": 0, "participantId": 6, "position": {"x": 9699, "y": 6336}, "timeEnemySpentControlled": 0, "totalGold": 500, "xp": 0}, "7": {"championStats": {"abilityHaste": 0, "abilityPower": 0, "armor": 36, "armorPen": 0, "armorPenPercent": 0, "attackDamage": 73, "attackSpeed": 103, "bonusArmorPenPercent": 0, "bonusMagicPenPercent": 0, "ccReduction": 0, "cooldownReduction": 0, "health": 585, "healthMax": 585, "healthRegen": 20, "lifesteal": 0, "magicPen": 0, "magicPenPercent": 0, "magicResist": 32, "movementSpeed": 345, "omnivamp": 0, "physicalVamp": 0, "power": 295, "powerMax": 295, "powerRegen": 16, "spellVamp": 0}, "currentGold": 0, "damageStats": {"magicDamageDone": 0, "magicDamageDoneToChampions": 0, "magicDamageTaken": 0, "physicalDamageDone": 0, "physicalDamageDoneToChampions": 0, "physicalDamageTaken": 0, "totalDamageDone": 0, "totalDamageDoneToChampions": 0, "totalDamageTaken": 0, "trueDamageDone": 0, "trueDamageDoneToChampions": 0, "trueDamageTaken": 0}, "goldPerSecond": 0, "jungleMinionsKilled": 0, "level": 1, "minionsKilled": 0, "participantId": 7, "position": {"x": 8641, "y": 6565}, "timeEnemySpentControlled": 0, "totalGold": 500, "xp": 0}, "8": {"championStats": {"abilityHaste": 0, "abilityPower": 0, "armor": 28, "armorPen": 0, "armorPenPercent": 0, "attackDamage": 86, "attackSpeed": 100, "bonusArmorPenPercent": 0, "bonusMagicPenPercent": 0, "ccReduction": 5, "cooldownReduction": 0, "health": 590, "healthMax": 590, "healthRegen": 15, "lifesteal": 0, "magicPen": 0, "magicPenPercent": 0, "magicResist": 40, "movementSpeed": 335, "omnivamp": 0, "physicalVamp": 0, "power": 320, "powerMax": 320, "powerRegen": 16, "spellVamp": 0}, "currentGold": 0, "damageStats": {"magicDamageDone": 0, "magicDamageDoneToChampions": 0, "magicDamageTaken": 0, "physicalDamageDone": 0, "physicalDamageDoneToChampions": 0, "physicalDamageTaken": 0, "totalDamageDone": 0, "totalDamageDoneToChampions": 0, "totalDamageTaken": 0, "trueDamageDone": 0, "trueDamageDoneToChampions": 0, "trueDamageTaken": 0}, "goldPerSecond": 0, "jungleMinionsKilled": 0, "level": 1, "minionsKilled": 0, "participantId": 8, "position": {"x": 8421, "y": 8837}, "timeEnemySpentControlled": 0, "totalGold": 500, "xp": 0}, "9": {"championStats": {"abilityHaste": 0, "abilityPower": 0, "armor": 35, "armorPen": 0, "armorPenPercent": 0, "attackDamage": 75, "attackSpeed": 110, "bonusArmorPenPercent": 0, "bonusMagicPenPercent": 0, "ccReduction": 0, "cooldownReduction": 0, "health": 605, "healthMax": 605, "healthRegen": 7, "lifesteal": 0, "magicPen": 0, "magicPenPercent": 0, "magicResist": 30, "movementSpeed": 330, "omnivamp": 0, "physicalVamp": 0, "power": 360, "powerMax": 360, "powerRegen": 16, "spellVamp": 0}, "currentGold": 0, "damageStats": {"magicDamageDone": 0, "magicDamageDoneToChampions": 0, "magicDamageTaken": 0, "physicalDamageDone": 0, "physicalDamageDoneToChampions": 0, "physicalDamageTaken": 0, "totalDamageDone": 0, "totalDamageDoneToChampions": 0, "totalDamageTaken": 0, "trueDamageDone": 0, "trueDamageDoneToChampions": 0, "trueDamageTaken": 0}, "goldPerSecond": 0, "jungleMinionsKilled": 0, "level": 1, "minionsKilled": 0, "participantId": 9, "position": {"x": 11842, "y": 6007}, "timeEnemySpentControlled": 0, "totalGold": 500, "xp": 0}, "10": {"championStats": {"abilityHaste": 0, "abilityPower": 5, "armor": 53, "armorPen": 0, "armorPenPercent": 0, "attackDamage": 60, "attackSpeed": 100, "bonusArmorPenPercent": 0, "bonusMagicPenPercent": 0, "ccReduction": 0, "cooldownReduction": 0, "health": 621, "healthMax": 621, "healthRegen": 21, "lifesteal": 0, "magicPen": 0, "magicPenPercent": 0, "magicResist": 32, "movementSpeed": 335, "omnivamp": 0, "physicalVamp": 0, "power": 302, "powerMax": 302, "powerRegen": 12, "spellVamp": 0}, "currentGold": 0, "damageStats": {"magicDamageDone": 0, "magicDamageDoneToChampions": 0, "magicDamageTaken": 0, "physicalDamageDone": 0, "physicalDamageDoneToChampions": 0, "physicalDamageTaken": 0, "totalDamageDone": 0, "totalDamageDoneToChampions": 0, "totalDamageTaken": 0, "trueDamageDone": 0, "trueDamageDoneToChampions": 0, "trueDamageTaken": 0}, "goldPerSecond": 20, "jungleMinionsKilled": 0, "level": 1, "minionsKilled": 0, "participantId": 10, "position": {"x": 12963, "y": 11764}, "timeEnemySpentControlled": 0, "totalGold": 500, "xp": 0}}, "timestamp": 60025}, {"events": [{"levelUpType": "NORMAL", "participantId": 2, "skillSlot": 2, "timestamp": 60126, "type": "SKILL_LEVEL_UP"}, {"levelUpType": "NORMAL", "participantId": 3, "skillSlot": 3, "timestamp": 73010, "type": "SKILL_LEVEL_UP"}, {"levelUpType": "NORMAL", "participantId": 7, "skillSlot": 2, "timestamp": 79155, "type": "SKILL_LEVEL_UP"}, {"levelUpType": "NORMAL", "participantId": 9, "skillSlot": 1, "timestamp": 82723, "type": "SKILL_LEVEL_UP"}, {"levelUpType": "NORMAL", "participantId": 8, "skillSlot": 1, "timestamp": 84112, "type": "SKILL_LEVEL_UP"}, {"levelUpType": "NORMAL", "participantId": 1, "skillSlot": 2, "timestamp": 93990, "type": "SKILL_LEVEL_UP"}, {"level": 2, "participantId": 7, "timestamp": 104828, "type": "LEVEL_UP"}, {"levelUpType": "NORMAL", "participantId": 7, "skillSlot": 3, "timestamp": 106049, "type": "SKILL_LEVEL_UP"}, {"level": 2, "participantId": 2, "timestamp": 109221, "type": "LEVEL_UP"}, {"levelUpType": "NORMAL", "participantId": 2, "skillSlot": 1, "timestamp": 110180, "type": "SKILL_LEVEL_UP"}, {"levelUpType": "NORMAL", "participantId": 6, "skillSlot": 1, "timestamp": 112756, "type": "SKILL_LEVEL_UP"}, {"level": 2, "participantId": 3, "timestamp": 113979, "type": "LEVEL_UP"}, {"levelUpType": "NORMAL", "participantId": 10, "skillSlot": 3, "timestamp": 115896, "type": "SKILL_LEVEL_UP"}, {"levelUpType": "NORMAL", "participantId": 3, "skillSlot": 2, "timestamp": 116986, "type": "SKILL_LEVEL_UP"}], "participantFrames": {"1": {"championStats": {"abilityHaste": 0, "abilityPower": 0, "armor": 41, "armorPen": 0, "armorPenPercent": 0, "attackDamage": 86, "attackSpeed": 100, "bonusArmorPenPercent": 0, "bonusMagicPenPercent": 0, "ccReduction": 0, "cooldownReduction": 0, "health": 620, "healthMax": 656, "healthRegen": 24, "lifesteal": 0, "magicPen": 0, "magicPenPercent": 0, "magicResist": 32, "movementSpeed": 340, "omnivamp": 2, "physicalVamp": 0, "power": 339, "powerMax": 339, "powerRegen": 16, "spellVamp": 0}, "currentGold": 98, "damageStats": {"magicDamageDone": 0, "magicDamageDoneToChampions": 0, "magicDamageTaken": 50, "physicalDamageDone": 435, "physicalDamageDoneToChampions": 0, "physicalDamageTaken": 0, "totalDamageDone": 435, "totalDamageDoneToChampions": 0, "totalDamageTaken": 50, "trueDamageDone": 0, "trueDamageDoneToChampions": 0, "trueDamageTaken": 0}, "goldPerSecond": 0, "jungleMinionsKilled": 0, "level": 1, "minionsKilled": 4, "participantId": 1, "position": {"x": 2419, "y": 12764}, "timeEnemySpentControlled": 0, "totalGold": 598, "xp": 222}, "2": {"championStats": {"abilityHaste": 0, "abilityPower": 9, "armor": 40, "armorPen": 0, "armorPenPercent": 0, "attackDamage": 60, "attackSpeed": 112, "bonusArmorPenPercent": 0, "bonusMagicPenPercent": 0, "ccReduction": 0, "cooldownReduction": 0, "health": 452, "healthMax": 646, "healthRegen": 32, "lifesteal": 0, "magicPen": 0, "magicPenPercent": 0, "magicResist": 32, "movementSpeed": 340, "omnivamp": 0, "physicalVamp": 0, "power": 282, "powerMax": 330, "powerRegen": 32, "spellVamp": 0}, "currentGold": 163, "damageStats": {"magicDamageDone": 1303, "magicDamageDoneToChampions": 0, "magicDamageTaken": 0, "physicalDamageDone": 988, "physicalDamageDoneToChampions": 0, "physicalDamageTaken": 647, "totalDamageDone": 2801, "totalDamageDoneToChampions": 0, "totalDamageTaken": 647, "trueDamageDone": 510, "trueDamageDoneToChampions": 0, "trueDamageTaken": 0}, "goldPerSecond": 0, "jungleMinionsKilled": 5, "level": 2, "minionsKilled": 1, "participantId": 2, "position": {"x": 8492, "y": 2441}, "timeEnemySpentControlled": 21681, "totalGold": 663, "xp": 418}, "3": {"championStats": {"abilityHaste": 0, "abilityPower": 24, "armor": 35, "armorPen": 0, "armorPenPercent": 0, "attackDamage": 63, "attackSpeed": 102, "bonusArmorPenPercent": 0, "bonusMagicPenPercent": 0, "ccReduction": 5, "cooldownReduction": 0, "health": 672, "healthMax": 677, "healthRegen": 19, "lifesteal": 0, "magicPen": 0, "magicPenPercent": 0, "magicResist": 33, "movementSpeed": 340, "omnivamp": 0, "physicalVamp": 0, "power": 360, "powerMax": 360, "powerRegen": 17, "spellVamp": 0}, "currentGold": 126, "damageStats": {"magicDamageDone": 0, "magicDamageDoneToChampions": 0, "magicDamageTaken": 0, "physicalDamageDone": 795, "physicalDamageDoneToChampions": 0, "physicalDamageTaken": 53, "totalDamageDone": 795, "totalDamageDoneToChampions": 0, "totalDamageTaken": 53, "trueDamageDone": 0, "trueDamageDoneToChampions": 0, "trueDamageTaken": 0}, "goldPerSecond": 0, "jungleMinionsKilled": 0, "level": 2, "minionsKilled": 6, "participantId": 3, "position": {"x": 7564, "y": 7780}, "timeEnemySpentControlled": 0, "totalGold": 626, "xp": 282}, "4": {"championStats": {"abilityHaste": 0, "abilityPower": 0, "armor": 32, "armorPen": 0, "armorPenPercent": 0, "attackDamage": 72, "attackSpeed": 110, "bonusArmorPenPercent": 0, "bonusMagicPenPercent": 0, "ccReduction": 0, "cooldownReduction": 0, "health": 650, "healthMax": 650, "healthRegen": 7, "lifesteal": 0, "magicPen": 0, "magicPenPercent": 0, "magicResist": 30, "movementSpeed": 325, "omnivamp": 2, "physicalVamp": 0, "power": 218, "powerMax": 280, "powerRegen": 13, "spellVamp": 0}, "currentGold": 84, "damageStats": {"magicDamageDone": 0, "magicDamageDoneToChampions": 0, "magicDamageTaken": 0, "physicalDamageDone": 961, "physicalDamageDoneToChampions": 0, "physicalDamageTaken": 0, "totalDamageDone": 961, "totalDamageDoneToChampions": 0, "totalDamageTaken": 0, "trueDamageDone": 0, "trueDamageDoneToChampions": 0, "trueDamageTaken": 0}, "goldPerSecond": 0, "jungleMinionsKilled": 0, "level": 1, "minionsKilled": 3, "participantId": 4, "position": {"x": 11065, "y": 1662}, "timeEnemySpentControlled": 15530, "totalGold": 584, "xp": 192}, "5": {"championStats": {"abilityHaste": 0, "abilityPower": 0, "armor": 38, "armorPen": 0, "armorPenPercent": 0, "attackDamage": 49, "attackSpeed": 100, "bonusArmorPenPercent": 0, "bonusMagicPenPercent": 0, "ccReduction": 0, "cooldownReduction": 0, "health": 480, "healthMax": 480, "healthRegen": 11, "lifesteal": 0, "magicPen": 0, "magicPenPercent": 0, "magicResist": 30, "movementSpeed": 328, "omnivamp": 0, "physicalVamp": 0, "power": 340, "powerMax": 340, "powerRegen": 23, "spellVamp": 0}, "currentGold": 521, "damageStats": {"magicDamageDone": 0, "magicDamageDoneToChampions": 0, "magicDamageTaken": 0, "physicalDamageDone": 0, "physicalDamageDoneToChampions": 0, "physicalDamageTaken": 0, "totalDamageDone": 0, "totalDamageDoneToChampions": 0, "totalDamageTaken": 0, "trueDamageDone": 0, "trueDamageDoneToChampions": 0, "trueDamageTaken": 0}, "goldPerSecond": 0, "jungleMinionsKilled": 0, "level": 1, "minionsKilled": 0, "participantId": 5, "position": {"x": 394, "y": 462}, "timeEnemySpentControlled": 0, "totalGold": 521, "xp": 0}, "6": {"championStats": {"abilityHaste": 0, "abilityPower": 0, "armor": 32, "armorPen": 0, "armorPenPercent": 0, "attackDamage": 60, "attackSpeed": 103, "bonusArmorPenPercent": 0, "bonusMagicPenPercent": 0, "ccReduction": 0, "cooldownReduction": 0, "health": 600, "healthMax": 600, "healthRegen": 10, "lifesteal": 0, "magicPen": 0, "magicPenPercent": 0, "magicResist": 26, "movementSpeed": 335, "omnivamp": 0, "physicalVamp": 0, "power": 273, "powerMax": 330, "powerRegen": 16, "spellVamp": 0}, "currentGold": 63, "damageStats": {"magicDamageDone": 249, "magicDamageDoneToChampions": 50, "magicDamageTaken": 0, "physicalDamageDone": 0, "physicalDamageDoneToChampions": 0, "physicalDamageTaken": 0, "totalDamageDone": 249, "totalDamageDoneToChampions": 50, "totalDamageTaken": 0, "trueDamageDone": 0, "trueDamageDoneToChampions": 0, "trueDamageTaken": 0}, "goldPerSecond": 0, "jungleMinionsKilled": 0, "level": 1, "minionsKilled": 2, "participantId": 6, "position": {"x": 3255, "y": 13190}, "timeEnemySpentControlled": 7499, "totalGold": 563, "xp": 181}, "7": {"championStats": {"abilityHaste": 0, "abilityPower": 0, "armor": 38, "armorPen": 0, "armorPenPercent": 0, "attackDamage": 76, "attackSpeed": 134, "bonusArmorPenPercent": 0, "bonusMagicPenPercent": 0, "ccReduction": 0, "cooldownReduction": 0, "health": 437, "healthMax": 646, "healthRegen": 21, "lifesteal": 0, "magicPen": 0, "magicPenPercent": 0, "magicResist": 32, "movementSpeed": 340, "omnivamp": 0, "physicalVamp": 0, "power": 341, "powerMax": 341, "powerRegen": 101, "spellVamp": 0}, "currentGold": 121, "damageStats": {"magicDamageDone": 272, "magicDamageDoneToChampions": 0, "magicDamageTaken": 137, "physicalDamageDone": 2019, "physicalDamageDoneToChampions": 0, "physicalDamageTaken": 286, "totalDamageDone": 2291, "totalDamageDoneToChampions": 0, "totalDamageTaken": 424, "trueDamageDone": 0, "trueDamageDoneToChampions": 0, "trueDamageTaken": 0}, "goldPerSecond": 0, "jungleMinionsKilled": 4, "level": 2, "minionsKilled": 0, "participantId": 7, "position": {"x": 12518, "y": 6372}, "timeEnemySpentControlled": 825, "totalGold": 621, "xp": 320}, "8": {"championStats": {"abilityHaste": 0, "abilityPower": 0, "armor": 28, "armorPen": 0, "armorPenPercent": 0, "attackDamage": 86, "attackSpeed": 100, "bonusArmorPenPercent": 0, "bonusMagicPenPercent": 0, "ccReduction": 5, "cooldownReduction": 0, "health": 590, "healthMax": 590, "healthRegen": 15, "lifesteal": 0, "magicPen": 0, "magicPenPercent": 0, "magicResist": 40, "movementSpeed": 335, "omnivamp": 0, "physicalVamp": 0, "power": 290, "powerMax": 320, "powerRegen": 16, "spellVamp": 0}, "currentGold": 84, "damageStats": {"magicDamageDone": 0, "magicDamageDoneToChampions": 0, "magicDamageTaken": 0, "physicalDamageDone": 390, "physicalDamageDoneToChampions": 0, "physicalDamageTaken": 0, "totalDamageDone": 390, "totalDamageDoneToChampions": 0, "totalDamageTaken": 0, "trueDamageDone": 0, "trueDamageDoneToChampions": 0, "trueDamageTaken": 0}, "goldPerSecond": 0, "jungleMinionsKilled": 0, "level": 1, "minionsKilled": 3, "participantId": 8, "position": {"x": 8314, "y": 8298}, "timeEnemySpentControlled": 0, "totalGold": 584, "xp": 181}, "9": {"championStats": {"abilityHaste": 0, "abilityPower": 0, "armor": 35, "armorPen": 0, "armorPenPercent": 0, "attackDamage": 75, "attackSpeed": 110, "bonusArmorPenPercent": 0, "bonusMagicPenPercent": 0, "ccReduction": 0, "cooldownReduction": 0, "health": 605, "healthMax": 605, "healthRegen": 7, "lifesteal": 0, "magicPen": 0, "magicPenPercent": 0, "magicResist": 30, "movementSpeed": 330, "omnivamp": 0, "physicalVamp": 0, "power": 323, "powerMax": 360, "powerRegen": 16, "spellVamp": 0}, "currentGold": 84, "damageStats": {"magicDamageDone": 0, "magicDamageDoneToChampions": 0, "magicDamageTaken": 0, "physicalDamageDone": 1142, "physicalDamageDoneToChampions": 0, "physicalDamageTaken": 0, "totalDamageDone": 1142, "totalDamageDoneToChampions": 0, "totalDamageTaken": 0, "trueDamageDone": 0, "trueDamageDoneToChampions": 0, "trueDamageTaken": 0}, "goldPerSecond": 0, "jungleMinionsKilled": 0, "level": 1, "minionsKilled": 3, "participantId": 9, "position": {"x": 12538, "y": 2226}, "timeEnemySpentControlled": 0, "totalGold": 584, "xp": 113}, "10": {"championStats": {"abilityHaste": 0, "abilityPower": 5, "armor": 53, "armorPen": 0, "armorPenPercent": 0, "attackDamage": 60, "attackSpeed": 100, "bonusArmorPenPercent": 0, "bonusMagicPenPercent": 0, "ccReduction": 0, "cooldownReduction": 0, "health": 621, "healthMax": 621, "healthRegen": 21, "lifesteal": 0, "magicPen": 0, "magicPenPercent": 0, "magicResist": 32, "movementSpeed": 335, "omnivamp": 0, "physicalVamp": 0, "power": 302, "powerMax": 302, "powerRegen": 12, "spellVamp": 0}, "currentGold": 23, "damageStats": {"magicDamageDone": 0, "magicDamageDoneToChampions": 0, "magicDamageTaken": 0, "physicalDamageDone": 306, "physicalDamageDoneToChampions": 0, "physicalDamageTaken": 50, "totalDamageDone": 306, "totalDamageDoneToChampions": 0, "totalDamageTaken": 50, "trueDamageDone": 0, "trueDamageDoneToChampions": 0, "trueDamageTaken": 0}, "goldPerSecond": 20, "jungleMinionsKilled": 0, "level": 1, "minionsKilled": 0, "participantId": 10, "position": {"x": 12387, "y": 1391}, "timeEnemySpentControlled": 0, "totalGold": 523, "xp": 113}}, "timestamp": 120028}, {"events": [{"level": 2, "participantId": 1, "timestamp": 132548, "type": "LEVEL_UP"}, {"levelUpType": "NORMAL", "participantId": 1, "skillSlot": 3, "timestamp": 134432, "type": "SKILL_LEVEL_UP"}, {"level": 2, "participantId": 9, "timestamp": 138197, "type": "LEVEL_UP"}, {"level": 2, "participantId": 10, "timestamp": 138197, "type": "LEVEL_UP"}, {"levelUpType": "NORMAL", "participantId": 10, "skillSlot": 1, "timestamp": 138594, "type": "SKILL_LEVEL_UP"}, {"levelUpType": "NORMAL", "participantId": 9, "skillSlot": 2, "timestamp": 139651, "type": "SKILL_LEVEL_UP"}, {"level": 2, "participantId": 8, "timestamp": 140608, "type": "LEVEL_UP"}, {"levelUpType": "NORMAL", "participantId": 8, "skillSlot": 2, "timestamp": 141632, "type": "SKILL_LEVEL_UP"}, {"level": 2, "participantId": 6, "timestamp": 142260, "type": "LEVEL_UP"}, {"levelUpType": "NORMAL", "participantId": 6, "skillSlot": 3, "timestamp": 143516, "type": "SKILL_LEVEL_UP"}, {"level": 3, "participantId": 7, "timestamp": 147612, "type": "LEVEL_UP"}, {"levelUpType": "NORMAL", "participantId": 7, "skillSlot": 1, "timestamp": 148768, "type": "SKILL_LEVEL_UP"}, {"level": 2, "participantId": 4, "timestamp": 150949, "type": "LEVEL_UP"}, {"level": 3, "participantId": 2, "timestamp": 154351, "type": "LEVEL_UP"}, {"levelUpType": "NORMAL", "participantId": 2, "skillSlot": 3, "timestamp": 157127, "type": "SKILL_LEVEL_UP"}, {"levelUpType": "NORMAL", "participantId": 4, "skillSlot": 1, "timestamp": 159704, "type": "SKILL_LEVEL_UP"}, {"level": 3, "participantId": 8, "timestamp": 160893, "type": "LEVEL_UP"}, {"level": 3, "participantId": 3, "timestamp": 161389, "type": "LEVEL_UP"}, {"levelUpType": "NORMAL", "participantId": 8, "skillSlot": 3, "timestamp": 161653, "type": "SKILL_LEVEL_UP"}, {"levelUpType": "NORMAL", "participantId": 3, "skillSlot": 1, "timestamp": 162346, "type": "SKILL_LEVEL_UP"}, {"level": 3, "participantId": 1, "timestamp": 166279, "type": "LEVEL_UP"}, {"levelUpType": "NORMAL", "participantId": 1, "skillSlot": 1, "timestamp": 167237, "type": "SKILL_LEVEL_UP"}, {"itemId": 2003, "participantId": 10, "timestamp": 174902, "type": "ITEM_DESTROYED"}, {"level": 3, "participantId": 6, "timestamp": 177048, "type": "LEVEL_UP"}, {"itemId": 2010, "participantId": 3, "timestamp": 177907, "type": "ITEM_DESTROYED"}, {"levelUpType": "NORMAL", "participantId": 6, "skillSlot": 2, "timestamp": 178006, "type": "SKILL_LEVEL_UP"}], "participantFrames": {"1": {"championStats": {"abilityHaste": 0, "abilityPower": 0, "armor": 46, "armorPen": 0, "armorPenPercent": 0, "attackDamage": 91, "attackSpeed": 103, "bonusArmorPenPercent": 0, "bonusMagicPenPercent": 0, "ccReduction": 0, "cooldownReduction": 0, "health": 745, "healthMax": 792, "healthRegen": 27, "lifesteal": 0, "magicPen": 0, "magicPenPercent": 0, "magicResist": 33, "movementSpeed": 340, "omnivamp": 2, "physicalVamp": 0, "power": 287, "powerMax": 415, "powerRegen": 18, "spellVamp": 0}, "currentGold": 490, "damageStats": {"magicDamageDone": 24, "magicDamageDoneToChampions": 24, "magicDamageTaken": 129, "physicalDamageDone": 2599, "physicalDamageDoneToChampions": 283, "physicalDamageTaken": 60, "totalDamageDone": 2686, "totalDamageDoneToChampions": 370, "totalDamageTaken": 190, "trueDamageDone": 61, "trueDamageDoneToChampions": 61, "trueDamageTaken": 0}, "goldPerSecond": 0, "jungleMinionsKilled": 0, "level": 3, "minionsKilled": 17, "participantId": 1, "position": {"x": 2904, "y": 13137}, "timeEnemySpentControlled": 7667, "totalGold": 990, "xp": 856}, "2": {"championStats": {"abilityHaste": 0, "abilityPower": 9, "armor": 42, "armorPen": 0, "armorPenPercent": 0, "attackDamage": 62, "attackSpeed": 114, "bonusArmorPenPercent": 0, "bonusMagicPenPercent": 0, "ccReduction": 0, "cooldownReduction": 0, "health": 539, "healthMax": 710, "healthRegen": 34, "lifesteal": 0, "magicPen": 0, "magicPenPercent": 0, "magicResist": 33, "movementSpeed": 340, "omnivamp": 0, "physicalVamp": 0, "power": 198, "powerMax": 383, "powerRegen": 77, "spellVamp": 0}, "currentGold": 564, "damageStats": {"magicDamageDone": 6054, "magicDamageDoneToChampions": 0, "magicDamageTaken": 0, "physicalDamageDone": 2685, "physicalDamageDoneToChampions": 0, "physicalDamageTaken": 1367, "totalDamageDone": 9581, "totalDamageDoneToChampions": 0, "totalDamageTaken": 1367, "trueDamageDone": 842, "trueDamageDoneToChampions": 0, "trueDamageTaken": 0}, "goldPerSecond": 0, "jungleMinionsKilled": 16, "level": 3, "minionsKilled": 1, "participantId": 2, "position": {"x": 3531, "y": 7769}, "timeEnemySpentControlled": 115001, "totalGold": 1064, "xp": 844}, "3": {"championStats": {"abilityHaste": 0, "abilityPower": 47, "armor": 38, "armorPen": 0, "armorPenPercent": 0, "attackDamage": 65, "attackSpeed": 105, "bonusArmorPenPercent": 0, "bonusMagicPenPercent": 0, "ccReduction": 5, "cooldownReduction": 0, "health": 209, "healthMax": 764, "healthRegen": 33, "lifesteal": 0, "magicPen": 0, "magicPenPercent": 0, "magicResist": 34, "movementSpeed": 340, "omnivamp": 0, "physicalVamp": 0, "power": 291, "powerMax": 463, "powerRegen": 75, "spellVamp": 0}, "currentGold": 409, "damageStats": {"magicDamageDone": 1027, "magicDamageDoneToChampions": 237, "magicDamageTaken": 53, "physicalDamageDone": 1686, "physicalDamageDoneToChampions": 49, "physicalDamageTaken": 694, "totalDamageDone": 2714, "totalDamageDoneToChampions": 286, "totalDamageTaken": 770, "trueDamageDone": 0, "trueDamageDoneToChampions": 0, "trueDamageTaken": 22}, "goldPerSecond": 0, "jungleMinionsKilled": 0, "level": 3, "minionsKilled": 15, "participantId": 3, "position": {"x": 7061, "y": 7009}, "timeEnemySpentControlled": 4722, "totalGold": 909, "xp": 793}, "4": {"championStats": {"abilityHaste": 0, "abilityPower": 0, "armor": 34, "armorPen": 0, "armorPenPercent": 0, "attackDamage": 74, "attackSpeed": 112, "bonusArmorPenPercent": 0, "bonusMagicPenPercent": 0, "ccReduction": 0, "cooldownReduction": 0, "health": 369, "healthMax": 712, "healthRegen": 7, "lifesteal": 0, "magicPen": 0, "magicPenPercent": 0, "magicResist": 30, "movementSpeed": 325, "omnivamp": 2, "physicalVamp": 0, "power": 186, "powerMax": 303, "powerRegen": 14, "spellVamp": 0}, "currentGold": 269, "damageStats": {"magicDamageDone": 0, "magicDamageDoneToChampions": 0, "magicDamageTaken": 73, "physicalDamageDone": 2098, "physicalDamageDoneToChampions": 146, "physicalDamageTaken": 292, "totalDamageDone": 2110, "totalDamageDoneToChampions": 158, "totalDamageTaken": 366, "trueDamageDone": 12, "trueDamageDoneToChampions": 12, "trueDamageTaken": 0}, "goldPerSecond": 0, "jungleMinionsKilled": 0, "level": 2, "minionsKilled": 6, "participantId": 4, "position": {"x": 9881, "y": 1187}, "timeEnemySpentControlled": 33769, "totalGold": 769, "xp": 553}, "5": {"championStats": {"abilityHaste": 0, "abilityPower": 0, "armor": 38, "armorPen": 0, "armorPenPercent": 0, "attackDamage": 49, "attackSpeed": 100, "bonusArmorPenPercent": 0, "bonusMagicPenPercent": 0, "ccReduction": 0, "cooldownReduction": 0, "health": 480, "healthMax": 480, "healthRegen": 11, "lifesteal": 0, "magicPen": 0, "magicPenPercent": 0, "magicResist": 30, "movementSpeed": 328, "omnivamp": 0, "physicalVamp": 0, "power": 340, "powerMax": 340, "powerRegen": 23, "spellVamp": 0}, "currentGold": 643, "damageStats": {"magicDamageDone": 0, "magicDamageDoneToChampions": 0, "magicDamageTaken": 0, "physicalDamageDone": 0, "physicalDamageDoneToChampions": 0, "physicalDamageTaken": 0, "totalDamageDone": 0, "totalDamageDoneToChampions": 0, "totalDamageTaken": 0, "trueDamageDone": 0, "trueDamageDoneToChampions": 0, "trueDamageTaken": 0}, "goldPerSecond": 0, "jungleMinionsKilled": 0, "level": 1, "minionsKilled": 0, "participantId": 5, "position": {"x": 394, "y": 462}, "timeEnemySpentControlled": 0, "totalGold": 643, "xp": 0}, "6": {"championStats": {"abilityHaste": 0, "abilityPower": 0, "armor": 36, "armorPen": 0, "armorPenPercent": 0, "attackDamage": 64, "attackSpeed": 123, "bonusArmorPenPercent": 0, "bonusMagicPenPercent": 0, "ccReduction": 0, "cooldownReduction": 0, "health": 559, "healthMax": 725, "healthRegen": 63, "lifesteal": 0, "magicPen": 0, "magicPenPercent": 0, "magicResist": 26, "movementSpeed": 431, "omnivamp": 0, "physicalVamp": 0, "power": 228, "powerMax": 403, "powerRegen": 66, "spellVamp": 0}, "currentGold": 276, "damageStats": {"magicDamageDone": 1042, "magicDamageDoneToChampions": 129, "magicDamageTaken": 24, "physicalDamageDone": 231, "physicalDamageDoneToChampions": 43, "physicalDamageTaken": 283, "totalDamageDone": 1273, "totalDamageDoneToChampions": 173, "totalDamageTaken": 370, "trueDamageDone": 0, "trueDamageDoneToChampions": 0, "trueDamageTaken": 61}, "goldPerSecond": 0, "jungleMinionsKilled": 0, "level": 3, "minionsKilled": 7, "participantId": 6, "position": {"x": 3786, "y": 13537}, "timeEnemySpentControlled": 31085, "totalGold": 776, "xp": 662}, "7": {"championStats": {"abilityHaste": 0, "abilityPower": 0, "armor": 41, "armorPen": 0, "armorPenPercent": 0, "attackDamage": 78, "attackSpeed": 137, "bonusArmorPenPercent": 0, "bonusMagicPenPercent": 0, "ccReduction": 0, "cooldownReduction": 0, "health": 512, "healthMax": 710, "healthRegen": 22, "lifesteal": 0, "magicPen": 0, "magicPenPercent": 0, "magicResist": 33, "movementSpeed": 340, "omnivamp": 0, "physicalVamp": 0, "power": 376, "powerMax": 390, "powerRegen": 113, "spellVamp": 0}, "currentGold": 513, "damageStats": {"magicDamageDone": 1584, "magicDamageDoneToChampions": 0, "magicDamageTaken": 313, "physicalDamageDone": 7462, "physicalDamageDoneToChampions": 0, "physicalDamageTaken": 914, "totalDamageDone": 9046, "totalDamageDoneToChampions": 0, "totalDamageTaken": 1228, "trueDamageDone": 0, "trueDamageDoneToChampions": 0, "trueDamageTaken": 0}, "goldPerSecond": 0, "jungleMinionsKilled": 16, "level": 3, "minionsKilled": 0, "participantId": 7, "position": {"x": 7318, "y": 10866}, "timeEnemySpentControlled": 8695, "totalGold": 1013, "xp": 815}, "8": {"championStats": {"abilityHaste": 0, "abilityPower": 0, "armor": 33, "armorPen": 0, "armorPenPercent": 0, "attackDamage": 91, "attackSpeed": 103, "bonusArmorPenPercent": 0, "bonusMagicPenPercent": 0, "ccReduction": 5, "cooldownReduction": 0, "health": 428, "healthMax": 722, "healthRegen": 17, "lifesteal": 0, "magicPen": 6, "magicPenPercent": 0, "magicResist": 41, "movementSpeed": 402, "omnivamp": 0, "physicalVamp": 0, "power": 157, "powerMax": 393, "powerRegen": 37, "spellVamp": 0}, "currentGold": 438, "damageStats": {"magicDamageDone": 134, "magicDamageDoneToChampions": 53, "magicDamageTaken": 237, "physicalDamageDone": 3056, "physicalDamageDoneToChampions": 564, "physicalDamageTaken": 90, "totalDamageDone": 3213, "totalDamageDoneToChampions": 640, "totalDamageTaken": 327, "trueDamageDone": 22, "trueDamageDoneToChampions": 22, "trueDamageTaken": 0}, "goldPerSecond": 0, "jungleMinionsKilled": 0, "level": 3, "minionsKilled": 14, "participantId": 8, "position": {"x": 7137, "y": 6923}, "timeEnemySpentControlled": 0, "totalGold": 948, "xp": 845}, "9": {"championStats": {"abilityHaste": 0, "abilityPower": 0, "armor": 37, "armorPen": 0, "armorPenPercent": 0, "attackDamage": 77, "attackSpeed": 111, "bonusArmorPenPercent": 0, "bonusMagicPenPercent": 0, "ccReduction": 0, "cooldownReduction": 0, "health": 581, "healthMax": 669, "healthRegen": 8, "lifesteal": 0, "magicPen": 0, "magicPenPercent": 0, "magicResist": 30, "movementSpeed": 330, "omnivamp": 0, "physicalVamp": 0, "power": 288, "powerMax": 388, "powerRegen": 17, "spellVamp": 0}, "currentGold": 497, "damageStats": {"magicDamageDone": 24, "magicDamageDoneToChampions": 24, "magicDamageTaken": 0, "physicalDamageDone": 3950, "physicalDamageDoneToChampions": 191, "physicalDamageTaken": 99, "totalDamageDone": 3975, "totalDamageDoneToChampions": 216, "totalDamageTaken": 99, "trueDamageDone": 0, "trueDamageDoneToChampions": 0, "trueDamageTaken": 0}, "goldPerSecond": 0, "jungleMinionsKilled": 0, "level": 2, "minionsKilled": 18, "participantId": 9, "position": {"x": 11020, "y": 1380}, "timeEnemySpentControlled": 0, "totalGold": 997, "xp": 564}, "10": {"championStats": {"abilityHaste": 0, "abilityPower": 5, "armor": 55, "armorPen": 0, "armorPenPercent": 0, "attackDamage": 62, "attackSpeed": 102, "bonusArmorPenPercent": 0, "bonusMagicPenPercent": 0, "ccReduction": 0, "cooldownReduction": 0, "health": 496, "healthMax": 694, "healthRegen": 122, "lifesteal": 0, "magicPen": 0, "magicPenPercent": 0, "magicResist": 32, "movementSpeed": 335, "omnivamp": 0, "physicalVamp": 0, "power": 243, "powerMax": 330, "powerRegen": 13, "spellVamp": 0}, "currentGold": 259, "damageStats": {"magicDamageDone": 256, "magicDamageDoneToChampions": 48, "magicDamageTaken": 0, "physicalDamageDone": 888, "physicalDamageDoneToChampions": 92, "physicalDamageTaken": 319, "totalDamageDone": 2095, "totalDamageDoneToChampions": 141, "totalDamageTaken": 331, "trueDamageDone": 950, "trueDamageDoneToChampions": 0, "trueDamageTaken": 12}, "goldPerSecond": 20, "jungleMinionsKilled": 0, "level": 2, "minionsKilled": 3, "participantId": 10, "position": {"x": 10830, "y": 1437}, "timeEnemySpentControlled": 991, "totalGold": 759, "xp": 564}}, "timestamp": 180054}, {"events": [{"bounty": 400, "killStreakLength": 0, "killerId": 8, "position": {"x": 6307, "y": 6781}, "timestamp": 183105, "type": "CHAMPION_KILL", "victimDamageDealt": [{"basic": false, "magicDamage": 34, "name": "Sylas", "participantId": 8, "physicalDamage": 0, "spellName": "sylasq", "spellSlot": 0, "trueDamage": 0, "type": "OTHER"}, {"basic": false, "magicDamage": 285, "name": "Sylas", "participantId": 8, "physicalDamage": 0, "spellName": "sylaspassive", "spellSlot": 63, "trueDamage": 0, "type": "OTHER"}, {"basic": false, "magicDamage": 70, "name": "Sylas", "participantId": 8, "physicalDamage": 0, "spellName": "sylasw", "spellSlot": 1, "trueDamage": 0, "type": "OTHER"}, {"basic": true, "magicDamage": 0, "name": "Sylas", "participantId": 8, "physicalDamage": 49, "spellName": "sylasbasicattack", "spellSlot": 64, "trueDamage": 0, "type": "OTHER"}, {"basic": false, "magicDamage": 99, "name": "Sylas", "participantId": 8, "physicalDamage": 0, "spellName": "sylase2", "spellSlot": 2, "trueDamage": 0, "type": "OTHER"}], "victimDamageReceived": [{"basic": true, "magicDamage": 0, "name": "SRU_ChaosMinionSiege", "participantId": 0, "physicalDamage": 59, "spellName": "sru_chaosminionsiegebasicattack", "spellSlot": 64, "trueDamage": 0, "type": "MINION"}, {"basic": false, "magicDamage": 0, "name": "Qiyana", "participantId": 8, "physicalDamage": 48, "spellName": "qiyanae", "spellSlot": 2, "trueDamage": 0, "type": "OTHER"}, {"basic": false, "magicDamage": 0, "name": "Qiyana", "participantId": 8, "physicalDamage": 50, "spellName": "qiyanapassive", "spellSlot": 63, "trueDamage": 0, "type": "OTHER"}, {"basic": false, "magicDamage": 53, "name": "Qiyana", "participantId": 8, "physicalDamage": 0, "spellName": "qiyanaw", "spellSlot": 1, "trueDamage": 0, "type": "OTHER"}, {"basic": false, "magicDamage": 0, "name": "Qiyana", "participantId": 8, "physicalDamage": 93, "spellName": "qiyanaq_rock", "spellSlot": 0, "trueDamage": 0, "type": "OTHER"}, {"basic": false, "magicDamage": 0, "name": "Qiyana", "participantId": 8, "physicalDamage": 58, "spellName": "qiyanaq_grass", "spellSlot": 0, "trueDamage": 0, "type": "OTHER"}, {"basic": false, "magicDamage": 0, "name": "Qiyana", "participantId": 8, "physicalDamage": 40, "spellName": "", "spellSlot": -1, "trueDamage": 0, "type": "OTHER"}, {"basic": true, "magicDamage": 0, "name": "Qiyana", "participantId": 8, "physicalDamage": 265, "spellName": "qiyanabasicattack", "spellSlot": 64, "trueDamage": 0, "type": "OTHER"}, {"basic": false, "magicDamage": 0, "name": "Qiyana", "participantId": 8, "physicalDamage": 0, "spellName": "summonerdot", "spellSlot": 5, "trueDamage": 88, "type": "OTHER"}], "victimId": 3}, {"killType": "KILL_FIRST_BLOOD", "killerId": 8, "position": {"x": 6404, "y": 6676}, "timestamp": 183105, "type": "CHAMPION_SPECIAL_KILL"}, {"itemId": 2003, "participantId": 4, "timestamp": 183435, "type": "ITEM_DESTROYED"}, {"itemId": 2010, "participantId": 4, "timestamp": 183633, "type": "ITEM_DESTROYED"}, {"bounty": 300, "killStreakLength": 0, "killerId": 3, "position": {"x": 6673, "y": 6771}, "timestamp": 184030, "type": "CHAMPION_KILL", "victimDamageReceived": [{"basic": false, "magicDamage": 34, "name": "Sylas", "participantId": 3, "physicalDamage": 0, "spellName": "sylasq", "spellSlot": 0, "trueDamage": 0, "type": "OTHER"}, {"basic": false, "magicDamage": 285, "name": "Sylas", "participantId": 3, "physicalDamage": 0, "spellName": "sylaspassive", "spellSlot": 63, "trueDamage": 0, "type": "OTHER"}, {"basic": false, "magicDamage": 70, "name": "Sylas", "participantId": 3, "physicalDamage": 0, "spellName": "sylasw", "spellSlot": 1, "trueDamage": 0, "type": "OTHER"}, {"basic": true, "magicDamage": 0, "name": "Sylas", "participantId": 3, "physicalDamage": 49, "spellName": "sylasbasicattack", "spellSlot": 64, "trueDamage": 0, "type": "OTHER"}, {"basic": false, "magicDamage": 99, "name": "Sylas", "participantId": 3, "physicalDamage": 0, "spellName": "sylase2", "spellSlot": 2, "trueDamage": 0, "type": "OTHER"}, {"basic": true, "magicDamage": 0, "name": "SRU_OrderMinionRanged", "participantId": 0, "physicalDamage": 9, "spellName": "sru_orderminionrangedbasicattack2", "spellSlot": 65, "trueDamage": 0, "type": "MINION"}, {"basic": true, "magicDamage": 0, "name": "SRU_OrderMinionRanged", "participantId": 0, "physicalDamage": 9, "spellName": "sru_orderminionrangedbasicattack", "spellSlot": 64, "trueDamage": 0, "type": "MINION"}, {"basic": true, "magicDamage": 0, "name": "SRUAP_Turret_Order1", "participantId": 0, "physicalDamage": 348, "spellName": "sruap_turret_order1basicattack", "spellSlot": 64, "trueDamage": 0, "type": "TOWER"}], "victimId": 8}, {"itemId": 1036, "participantId": 8, "timestamp": 186507, "type": "ITEM_DESTROYED"}, {"itemId": 3134, "participantId": 8, "timestamp": 186507, "type": "ITEM_PURCHASED"}, {"assistingParticipantIds": [9], "bounty": 300, "killStreakLength": 0, "killerId": 10, "position": {"x": 8411, "y": 851}, "timestamp": 186607, "type": "CHAMPION_KILL", "victimDamageReceived": [{"basic": false, "magicDamage": 24, "name": "Leona", "participantId": 10, "physicalDamage": 0, "spellName": "leonasunlightpassive", "spellSlot": 63, "trueDamage": 0, "type": "OTHER"}, {"basic": false, "magicDamage": 39, "name": "Leona", "participantId": 10, "physicalDamage": 0, "spellName": "leonazenithblade", "spellSlot": 2, "trueDamage": 0, "type": "OTHER"}, {"basic": true, "magicDamage": 0, "name": "Leona", "participantId": 10, "physicalDamage": 46, "spellName": "leonabasicattack", "spellSlot": 64, "trueDamage": 0, "type": "OTHER"}, {"basic": false, "magicDamage": 8, "name": "Leona", "participantId": 10, "physicalDamage": 46, "spellName": "leonashieldofdaybreak", "spellSlot": 0, "trueDamage": 0, "type": "OTHER"}, {"basic": false, "magicDamage": 0, "name": "Leona", "participantId": 10, "physicalDamage": 0, "spellName": "summonerdot", "spellSlot": 4, "trueDamage": 54, "type": "OTHER"}, {"basic": false, "magicDamage": 0, "name": "Draven", "participantId": 9, "physicalDamage": 191, "spellName": "dravenspinning", "spellSlot": 0, "trueDamage": 0, "type": "OTHER"}], "victimId": 4}, {"itemId": 1028, "participantId": 3, "timestamp": 187729, "type": "ITEM_PURCHASED"}, {"itemId": 1001, "participantId": 3, "timestamp": 188522, "type": "ITEM_PURCHASED"}, {"gameId": 4055809243, "realTimestamp": 1632856278919, "timestamp": 194270, "type": "GAME_END", "winningTeam": 200}], "participantFrames": {"1": {"championStats": {"abilityHaste": 0, "abilityPower": 0, "armor": 46, "armorPen": 0, "armorPenPercent": 0, "attackDamage": 91, "attackSpeed": 103, "bonusArmorPenPercent": 0, "bonusMagicPenPercent": 0, "ccReduction": 0, "cooldownReduction": 0, "health": 780, "healthMax": 792, "healthRegen": 19, "lifesteal": 0, "magicPen": 0, "magicPenPercent": 0, "magicResist": 33, "movementSpeed": 340, "omnivamp": 2, "physicalVamp": 0, "power": 263, "powerMax": 415, "powerRegen": 18, "spellVamp": 0}, "currentGold": 568, "damageStats": {"magicDamageDone": 24, "magicDamageDoneToChampions": 24, "magicDamageTaken": 129, "physicalDamageDone": 2960, "physicalDamageDoneToChampions": 283, "physicalDamageTaken": 68, "totalDamageDone": 3109, "totalDamageDoneToChampions": 370, "totalDamageTaken": 198, "trueDamageDone": 123, "trueDamageDoneToChampions": 61, "trueDamageTaken": 0}, "goldPerSecond": 0, "jungleMinionsKilled": 0, "level": 3, "minionsKilled": 20, "participantId": 1, "position": {"x": 3215, "y": 13411}, "timeEnemySpentControlled": 7667, "totalGold": 1068, "xp": 976}, "2": {"championStats": {"abilityHaste": 0, "abilityPower": 9, "armor": 42, "armorPen": 0, "armorPenPercent": 0, "attackDamage": 62, "attackSpeed": 114, "bonusArmorPenPercent": 0, "bonusMagicPenPercent": 0, "ccReduction": 0, "cooldownReduction": 0, "health": 603, "healthMax": 710, "healthRegen": 34, "lifesteal": 0, "magicPen": 0, "magicPenPercent": 0, "magicResist": 33, "movementSpeed": 340, "omnivamp": 0, "physicalVamp": 0, "power": 249, "powerMax": 383, "powerRegen": 60, "spellVamp": 0}, "currentGold": 593, "damageStats": {"magicDamageDone": 6425, "magicDamageDoneToChampions": 0, "magicDamageTaken": 0, "physicalDamageDone": 3101, "physicalDamageDoneToChampions": 0, "physicalDamageTaken": 1641, "totalDamageDone": 10891, "totalDamageDoneToChampions": 0, "totalDamageTaken": 1641, "trueDamageDone": 1364, "trueDamageDoneToChampions": 0, "trueDamageTaken": 0}, "goldPerSecond": 0, "jungleMinionsKilled": 16, "level": 3, "minionsKilled": 1, "participantId": 2, "position": {"x": 3474, "y": 7840}, "timeEnemySpentControlled": 126794, "totalGold": 1093, "xp": 844}, "3": {"championStats": {"abilityHaste": 0, "abilityPower": 24, "armor": 38, "armorPen": 0, "armorPenPercent": 0, "attackDamage": 65, "attackSpeed": 105, "bonusArmorPenPercent": 0, "bonusMagicPenPercent": 0, "ccReduction": 7, "cooldownReduction": 0, "health": 914, "healthMax": 914, "healthRegen": 20, "lifesteal": 0, "magicPen": 0, "magicPenPercent": 0, "magicResist": 34, "movementSpeed": 595, "omnivamp": 0, "physicalVamp": 0, "power": 463, "powerMax": 463, "powerRegen": 18, "spellVamp": 0}, "currentGold": 38, "damageStats": {"magicDamageDone": 1281, "magicDamageDoneToChampions": 490, "magicDamageTaken": 69, "physicalDamageDone": 1686, "physicalDamageDoneToChampions": 49, "physicalDamageTaken": 882, "totalDamageDone": 2967, "totalDamageDoneToChampions": 539, "totalDamageTaken": 1039, "trueDamageDone": 0, "trueDamageDoneToChampions": 0, "trueDamageTaken": 88}, "goldPerSecond": 0, "jungleMinionsKilled": 0, "level": 3, "minionsKilled": 15, "participantId": 3, "position": {"x": 271, "y": 455}, "timeEnemySpentControlled": 6010, "totalGold": 1238, "xp": 979}, "4": {"championStats": {"abilityHaste": 0, "abilityPower": 0, "armor": 34, "armorPen": 0, "armorPenPercent": 0, "attackDamage": 74, "attackSpeed": 112, "bonusArmorPenPercent": 0, "bonusMagicPenPercent": 0, "ccReduction": 0, "cooldownReduction": 0, "health": 0, "healthMax": 712, "healthRegen": 7, "lifesteal": 0, "magicPen": 0, "magicPenPercent": 0, "magicResist": 30, "movementSpeed": 325, "omnivamp": 2, "physicalVamp": 0, "power": 252, "powerMax": 353, "powerRegen": 14, "spellVamp": 0}, "currentGold": 298, "damageStats": {"magicDamageDone": 0, "magicDamageDoneToChampions": 0, "magicDamageTaken": 146, "physicalDamageDone": 2098, "physicalDamageDoneToChampions": 146, "physicalDamageTaken": 576, "totalDamageDone": 2110, "totalDamageDoneToChampions": 158, "totalDamageTaken": 777, "trueDamageDone": 12, "trueDamageDoneToChampions": 12, "trueDamageTaken": 54}, "goldPerSecond": 0, "jungleMinionsKilled": 0, "level": 2, "minionsKilled": 6, "participantId": 4, "position": {"x": 8411, "y": 851}, "timeEnemySpentControlled": 33769, "totalGold": 798, "xp": 614}, "5": {"championStats": {"abilityHaste": 0, "abilityPower": 0, "armor": 38, "armorPen": 0, "armorPenPercent": 0, "attackDamage": 49, "attackSpeed": 100, "bonusArmorPenPercent": 0, "bonusMagicPenPercent": 0, "ccReduction": 0, "cooldownReduction": 0, "health": 480, "healthMax": 480, "healthRegen": 11, "lifesteal": 0, "magicPen": 0, "magicPenPercent": 0, "magicResist": 30, "movementSpeed": 328, "omnivamp": 0, "physicalVamp": 0, "power": 340, "powerMax": 340, "powerRegen": 23, "spellVamp": 0}, "currentGold": 672, "damageStats": {"magicDamageDone": 0, "magicDamageDoneToChampions": 0, "magicDamageTaken": 0, "physicalDamageDone": 0, "physicalDamageDoneToChampions": 0, "physicalDamageTaken": 0, "totalDamageDone": 0, "totalDamageDoneToChampions": 0, "totalDamageTaken": 0, "trueDamageDone": 0, "trueDamageDoneToChampions": 0, "trueDamageTaken": 0}, "goldPerSecond": 0, "jungleMinionsKilled": 0, "level": 1, "minionsKilled": 0, "participantId": 5, "position": {"x": 394, "y": 462}, "timeEnemySpentControlled": 0, "totalGold": 672, "xp": 0}, "6": {"championStats": {"abilityHaste": 0, "abilityPower": 0, "armor": 36, "armorPen": 0, "armorPenPercent": 0, "attackDamage": 64, "attackSpeed": 105, "bonusArmorPenPercent": 0, "bonusMagicPenPercent": 0, "ccReduction": 0, "cooldownReduction": 0, "health": 599, "healthMax": 725, "healthRegen": 11, "lifesteal": 0, "magicPen": 0, "magicPenPercent": 0, "magicResist": 26, "movementSpeed": 335, "omnivamp": 0, "physicalVamp": 0, "power": 270, "powerMax": 403, "powerRegen": 18, "spellVamp": 0}, "currentGold": 305, "damageStats": {"magicDamageDone": 1042, "magicDamageDoneToChampions": 129, "magicDamageTaken": 24, "physicalDamageDone": 231, "physicalDamageDoneToChampions": 43, "physicalDamageTaken": 283, "totalDamageDone": 1273, "totalDamageDoneToChampions": 173, "totalDamageTaken": 370, "trueDamageDone": 0, "trueDamageDoneToChampions": 0, "trueDamageTaken": 61}, "goldPerSecond": 0, "jungleMinionsKilled": 0, "level": 3, "minionsKilled": 7, "participantId": 6, "position": {"x": 5088, "y": 13579}, "timeEnemySpentControlled": 31085, "totalGold": 805, "xp": 662}, "7": {"championStats": {"abilityHaste": 0, "abilityPower": 0, "armor": 41, "armorPen": 0, "armorPenPercent": 0, "attackDamage": 78, "attackSpeed": 107, "bonusArmorPenPercent": 0, "bonusMagicPenPercent": 0, "ccReduction": 0, "cooldownReduction": 0, "health": 503, "healthMax": 710, "healthRegen": 37, "lifesteal": 0, "magicPen": 0, "magicPenPercent": 0, "magicResist": 33, "movementSpeed": 345, "omnivamp": 0, "physicalVamp": 0, "power": 390, "powerMax": 390, "powerRegen": 107, "spellVamp": 0}, "currentGold": 642, "damageStats": {"magicDamageDone": 1654, "magicDamageDoneToChampions": 0, "magicDamageTaken": 313, "physicalDamageDone": 8160, "physicalDamageDoneToChampions": 0, "physicalDamageTaken": 1028, "totalDamageDone": 9814, "totalDamageDoneToChampions": 0, "totalDamageTaken": 1342, "trueDamageDone": 0, "trueDamageDoneToChampions": 0, "trueDamageTaken": 0}, "goldPerSecond": 0, "jungleMinionsKilled": 20, "level": 3, "minionsKilled": 0, "participantId": 7, "position": {"x": 5874, "y": 9456}, "timeEnemySpentControlled": 8695, "totalGold": 1142, "xp": 985}, "8": {"championStats": {"abilityHaste": 0, "abilityPower": 0, "armor": 28, "armorPen": 0, "armorPenPercent": 0, "attackDamage": 25, "attackSpeed": 100, "bonusArmorPenPercent": 0, "bonusMagicPenPercent": 0, "ccReduction": 0, "cooldownReduction": 0, "health": 722, "healthMax": 722, "healthRegen": 0, "lifesteal": 0, "magicPen": 0, "magicPenPercent": 0, "magicResist": 32, "movementSpeed": 335, "omnivamp": 0, "physicalVamp": 0, "power": 393, "powerMax": 393, "powerRegen": 0, "spellVamp": 0}, "currentGold": 117, "damageStats": {"magicDamageDone": 150, "magicDamageDoneToChampions": 69, "magicDamageTaken": 490, "physicalDamageDone": 3244, "physicalDamageDoneToChampions": 752, "physicalDamageTaken": 438, "totalDamageDone": 3482, "totalDamageDoneToChampions": 909, "totalDamageTaken": 929, "trueDamageDone": 88, "trueDamageDoneToChampions": 88, "trueDamageTaken": 0}, "goldPerSecond": 0, "jungleMinionsKilled": 0, "level": 3, "minionsKilled": 14, "participantId": 8, "position": {"x": 14340, "y": 14391}, "timeEnemySpentControlled": 0, "totalGold": 1377, "xp": 1031}, "9": {"championStats": {"abilityHaste": 0, "abilityPower": 0, "armor": 37, "armorPen": 0, "armorPenPercent": 0, "attackDamage": 79, "attackSpeed": 111, "bonusArmorPenPercent": 0, "bonusMagicPenPercent": 0, "ccReduction": 0, "cooldownReduction": 0, "health": 623, "healthMax": 669, "healthRegen": 8, "lifesteal": 0, "magicPen": 0, "magicPenPercent": 0, "magicResist": 30, "movementSpeed": 330, "omnivamp": 1, "physicalVamp": 0, "power": 212, "powerMax": 388, "powerRegen": 17, "spellVamp": 0}, "currentGold": 661, "damageStats": {"magicDamageDone": 49, "magicDamageDoneToChampions": 49, "magicDamageTaken": 0, "physicalDamageDone": 4460, "physicalDamageDoneToChampions": 383, "physicalDamageTaken": 170, "totalDamageDone": 4509, "totalDamageDoneToChampions": 432, "totalDamageTaken": 170, "trueDamageDone": 0, "trueDamageDoneToChampions": 0, "trueDamageTaken": 0}, "goldPerSecond": 0, "jungleMinionsKilled": 0, "level": 2, "minionsKilled": 18, "participantId": 9, "position": {"x": 9277, "y": 1301}, "timeEnemySpentControlled": 0, "totalGold": 1161, "xp": 602}, "10": {"championStats": {"abilityHaste": 0, "abilityPower": 5, "armor": 55, "armorPen": 0, "armorPenPercent": 0, "attackDamage": 62, "attackSpeed": 102, "bonusArmorPenPercent": 0, "bonusMagicPenPercent": 0, "ccReduction": 0, "cooldownReduction": 0, "health": 691, "healthMax": 694, "healthRegen": 22, "lifesteal": 0, "magicPen": 0, "magicPenPercent": 0, "magicResist": 32, "movementSpeed": 335, "omnivamp": 0, "physicalVamp": 0, "power": 156, "powerMax": 330, "powerRegen": 13, "spellVamp": 0}, "currentGold": 591, "damageStats": {"magicDamageDone": 414, "magicDamageDoneToChampions": 97, "magicDamageTaken": 0, "physicalDamageDone": 980, "physicalDamageDoneToChampions": 184, "physicalDamageTaken": 361, "totalDamageDone": 2399, "totalDamageDoneToChampions": 336, "totalDamageTaken": 373, "trueDamageDone": 1004, "trueDamageDoneToChampions": 54, "trueDamageTaken": 12}, "goldPerSecond": 20, "jungleMinionsKilled": 0, "level": 2, "minionsKilled": 3, "participantId": 10, "position": {"x": 9602, "y": 1596}, "timeEnemySpentControlled": 2842, "totalGold": 1091, "xp": 602}}, "timestamp": 194270}], "gameId": 4055809243, "participants": [{"participantId": 1, "puuid": "JF77qXxvJVLRNsMBh6GD4gAB0iDggHKPkTgBj7azoDICf-wsQKRLc-iublCPndvFC6N0GGmYeAdnmQ"}, {"participantId": 2, "puuid": "9Y6ck-DOgT_QxtsP6g0LKVHaDGAYDV0AJBlQkNxYHqjQxrpGvZvpKyeqwSSNRWp-63wOVaxR9D7qGA"}, {"participantId": 3, "puuid": "hvQzNBE11nlPh3jMdYDIT3LR4o4HY59lSQPXwLOtsD-NSQfAXJzOFXaPGhDSlaVypabundI7BFLJnQ"}, {"participantId": 4, "puuid": "ZioJPINUMQH-A0hR52DTtlJZK6244QxX-FIZ6TLzBOFS2hIqLnhSIXVdNt90GPR_g7o8gWh9DorhYA"}, {"participantId": 5, "puuid": "6BlInRmPv5KB0RlxEuRnD0-Ys5h94m6pLKMhGKI6OF059J1ElMnruF6doLYe1aLprhdpwoMN6bq7cw"}, {"participantId": 6, "puuid": "QxDrFSB4JTAmOsmAkGMLvFnUWYElWPdktiB9dnkOPcqLuecUxTbMGgnAqp2jodPkJLEece8fNHai0A"}, {"participantId": 7, "puuid": "1nyzmxLyhiaML7MqFZY0IYxOam8O_xAKAHo1QNVMNBp-DrAqu8zkIQCNxcsOGsBshlTZ2ByqE7fmYQ"}, {"participantId": 8, "puuid": "vnTza7GKACnddu8YEMsM1TFJWGxmEV88ajFPnQ_yujAfxhnuKceEnU0k20T9rxnYE4zahwp4uyRXVA"}, {"participantId": 9, "puuid": "DlhFyUDdIjGtLPxuGkoTo0c0XPHXZ1pyM75Tfbju4Wvc8XRdE2aSo2BRtykpOyuix6bRvuplFYzZkg"}, {"participantId": 10, "puuid": "38WQGMdvGsE0pqibCVOM6Q5W4aWrcOr5Z8xofm2DVvbHDaHRFQ-Vudz-aTdKVMa9A6bmDZH7-H_Qqw"}]}}